{
    "Ar36": {
        "error": 0.00027734388993863173,
        "error_type": "SEM",
        "filter_outliers_dict": {
            "filter_outliers": true,
            "iterations": 1,
            "std_devs": 3,
            "use_iqr_filtering": false,
            "use_standard_deviation_filtering": false
        },
        "fit": "Parabolic",
        "fn": 398,
        "include_baseline_error": true,
        "n": 400,
        "outlier_excluded": [
            386,
            219
        ],
        "reviewed": true,
        "user_excluded": [],
        "value": 0.012219031373837697
    },
    "Ar37": {
        "error": 0.003221623301457927,
        "error_type": "SEM",
        "filter_outliers_dict": {
            "filter_outliers": true,
            "iterations": 1,
            "std_devs": 3,
            "use_iqr_filtering": false,
            "use_standard_deviation_filtering": false
        },
        "fit": "Linear",
        "fn": 399,
        "include_baseline_error": true,
        "n": 400,
        "outlier_excluded": [
            40
        ],
        "reviewed": true,
        "user_excluded": [],
        "value": 0.13858414572720384
    },
    "Ar38": {
        "error": 0.00259138543974964,
        "error_type": "SEM",
        "filter_outliers_dict": {
            "filter_outliers": true,
            "iterations": 1,
            "std_devs": 3,
            "use_iqr_filtering": false,
            "use_standard_deviation_filtering": false
        },
        "fit": "Linear",
        "fn": 397,
        "include_baseline_error": true,
        "n": 400,
        "outlier_excluded": [
            57,
            130,
            141
        ],
        "reviewed": true,
        "user_excluded": [],
        "value": 0.42425715165935735
    },
    "Ar39": {
        "error": 0.012966197314150154,
        "error_type": "SEM",
        "filter_outliers_dict": {
            "filter_outliers": true,
            "iterations": 1,
            "std_devs": 3,
            "use_iqr_filtering": false,
            "use_standard_deviation_filtering": false
        },
        "fit": "Parabolic",
        "fn": 400,
        "include_baseline_error": true,
        "n": 400,
        "outlier_excluded": [],
        "reviewed": true,
        "user_excluded": [],
        "value": 32.29912282950582
    },
    "Ar40": {
        "error": 0.012633078409399133,
        "error_type": "SEM",
        "filter_outliers_dict": {
            "filter_outliers": true,
            "iterations": 1,
            "std_devs": 3,
            "use_iqr_filtering": false,
            "use_standard_deviation_filtering": false
        },
        "fit": "Parabolic",
        "fn": 400,
        "include_baseline_error": true,
        "n": 400,
        "outlier_excluded": [],
        "reviewed": true,
        "user_excluded": [],
        "value": 43.34673635967527
    },
    "Ar41": {
        "error": 0.02757513549272336,
        "error_type": "SEM",
        "filter_outliers_dict": {
            "filter_outliers": true,
            "iterations": 1,
            "std_devs": 2
        },
        "fit": "linear",
        "value": -0.2806409608284235
    }
}