{
    "AX": {
        "error": 0.007486785171299644,
        "error_type": "SEM",
        "filter_outliers_dict": {
            "filter_outliers": true,
            "iterations": 1,
            "std_devs": 2
        },
        "fit": "Average",
        "fn": 43,
        "include_baseline_error": false,
        "n": 45,
        "reviewed": true,
        "value": -0.03150045169993888
    },
    "CDD": {
        "error": 4.74967253528443e-06,
        "error_type": "SEM",
        "filter_outliers_dict": {
            "filter_outliers": true,
            "iterations": 1,
            "std_devs": 10
        },
        "fit": "Average",
        "fn": 45,
        "include_baseline_error": false,
        "n": 45,
        "reviewed": true,
        "value": 6.794707668531272e-06
    },
    "H1": {
        "error": 0.006733624716657422,
        "error_type": "SEM",
        "filter_outliers_dict": {
            "filter_outliers": true,
            "iterations": 1,
            "std_devs": 2
        },
        "fit": "Average",
        "fn": 44,
        "include_baseline_error": false,
        "n": 45,
        "reviewed": true,
        "value": -0.004299204476410523
    },
    "H2": {
        "error": 0.00662474891470432,
        "error_type": "SEM",
        "filter_outliers_dict": {
            "filter_outliers": true,
            "iterations": 1,
            "std_devs": 2
        },
        "fit": "average",
        "value": -0.032788671002009696
    },
    "L1": {
        "error": 0.005281236750898961,
        "error_type": "SEM",
        "filter_outliers_dict": {
            "filter_outliers": true,
            "iterations": 1,
            "std_devs": 2
        },
        "fit": "Average",
        "fn": 43,
        "include_baseline_error": false,
        "n": 45,
        "reviewed": true,
        "value": -0.012531164735772236
    },
    "L2": {
        "error": 0.0070097701741411046,
        "error_type": "SEM",
        "filter_outliers_dict": {
            "filter_outliers": true,
            "iterations": 1,
            "std_devs": 2
        },
        "fit": "Average",
        "fn": 42,
        "include_baseline_error": false,
        "n": 45,
        "reviewed": true,
        "value": -0.33381718751930056
    }
}