{
    "Ar36": {
        "error": 0.00019756319958684447,
        "error_type": "",
        "fit": "previous",
        "references": [
            {
                "exclude": false,
                "record_id": "bc-02-J-1466"
            }
        ],
        "value": 0.0027464523791817484
    },
    "Ar37": {
        "error": 0.0058193086928103885,
        "error_type": "",
        "fit": "previous",
        "references": [
            {
                "exclude": false,
                "record_id": "bc-02-J-1466"
            }
        ],
        "value": 0.022544288255056555
    },
    "Ar38": {
        "error": 0.00533891977765019,
        "error_type": "",
        "fit": "previous",
        "references": [
            {
                "exclude": false,
                "record_id": "bc-02-J-1466"
            }
        ],
        "value": 0.008865469711719642
    },
    "Ar39": {
        "error": 0.011689070596396775,
        "error_type": "",
        "fit": "previous",
        "references": [
            {
                "exclude": false,
                "record_id": "bc-02-J-1466"
            }
        ],
        "value": 0.059357602395880435
    },
    "Ar40": {
        "error": 0.008309275666336971,
        "error_type": "",
        "fit": "previous",
        "references": [
            {
                "exclude": false,
                "record_id": "bc-02-J-1466"
            }
        ],
        "value": 0.24361592675754584
    },
    "Ar41": {
        "error": 0.005495482636198913,
        "error_type": "",
        "fit": "previous",
        "references": [
            {
                "exclude": false,
                "record_id": "bc-02-J-1466"
            }
        ],
        "value": 0.024874263041688473
    }
}